idrlnet/__init__.py
idrlnet/callbacks.py
idrlnet/data.py
idrlnet/graph.py
idrlnet/header.py
idrlnet/net.py
idrlnet/node.py
idrlnet/optim.py
idrlnet/pde.py
idrlnet/receivers.py
idrlnet/shortcut.py
idrlnet/solver.py
idrlnet/torch_util.py
idrlnet/variable.py
idrlnet/architecture/__init__.py
idrlnet/architecture/grid.py
idrlnet/architecture/layer.py
idrlnet/architecture/mlp.py
idrlnet/geo_utils/__init__.py
idrlnet/geo_utils/geo.py
idrlnet/geo_utils/geo_builder.py
idrlnet/geo_utils/geo_obj.py
idrlnet/geo_utils/sympy_np.py
idrlnet/pde_op/__init__.py
idrlnet/pde_op/equations.py
idrlnet/pde_op/operator.py
idrlnet-2.0.0.dist-info/LICENSE
idrlnet-2.0.0.dist-info/METADATA
idrlnet-2.0.0.dist-info/WHEEL
idrlnet-2.0.0.dist-info/top_level.txt
idrlnet-2.0.0.dist-info/RECORD
