Metadata-Version: 2.1
Name: idrlnet
Version: 2.0.0
Summary: IDRLnet
Home-page: https://github.com/idrl-lab/idrlnet
Author: Intelligent Design & Robust Learning lab
Author-email: weipeng@deepinfar.cn
License: UNKNOWN
Platform: UNKNOWN
Classifier: Programming Language :: Python :: 3
Classifier: Programming Language :: Python :: 3.7
Classifier: Programming Language :: Python :: 3.8
Classifier: Programming Language :: Python :: 3.9
Classifier: License :: OSI Approved :: Apache Software License
Classifier: Operating System :: OS Independent
Classifier: Environment :: Console
Classifier: Intended Audience :: Developers
Classifier: Topic :: Scientific/Engineering :: Artificial Intelligence
Requires-Python: >=3.6
Requires-Dist: transforms3d
Requires-Dist: typing
Requires-Dist: keras
Requires-Dist: h5py
Requires-Dist: pandas
Requires-Dist: zipfile36
Requires-Dist: scikit-optimize
Requires-Dist: pytest
Requires-Dist: sphinx
Requires-Dist: matplotlib
Requires-Dist: myst-parser
Requires-Dist: sphinx-markdown-parser
Requires-Dist: numpy (==1.21.0)
Requires-Dist: sphinx-rtd-theme (==0.5.2)
Requires-Dist: tensorboard (==2.4.1)
Requires-Dist: sympy (==1.5.1)
Requires-Dist: pyevtk (==1.1.1)
Requires-Dist: flask (==1.1.2)
Requires-Dist: requests (==2.25.0)
Requires-Dist: torch (==1.7.1)
Requires-Dist: networkx (==2.5.1)
Requires-Dist: protobuf (~=3.20)
